{
    "type": "fromPhysicsEditor",
    "label": "pipe",
    "isStatic": true,
    "density": 0.1,
    "restitution": 0,
    "friction": 0.1,
    "frictionAir": 0.01,
    "frictionStatic": 0.5,
    "collisionFilter": {
        "group": 0,
        "category": 1,
        "mask": 255
    },
    "fixtures": [
        {
            "label": "pipe",
            "type": "POLYGON",
            "isSensor": true,
            "vertices": [
                [
                    {
                        "x": 8.049964904785156,
                        "y": 0.6250839233398438
                    },
                    {
                        "x": 58.674957275390625,
                        "y": -0.72491455078125
                    },
                    {
                        "x": 57.94997787475586,
                        "y": 390.4501037597656
                    },
                    {
                        "x": 64.5999755859375,
                        "y": 393.30010986328125
                    },
                    {
                        "x": 64.5999755859375,
                        "y": 411.35009765625
                    },
                    {
                        "x": 0.9499921798706055,
                        "y": 410.40008544921875
                    },
                    {
                        "x": -0.9500083923339844,
                        "y": 394.2500915527344
                    },
                    {
                        "x": 3.999995231628418,
                        "y": 388.7500915527344
                    }
                ]
            ]
        }
    ]
}